setup.py
test/test.py
test/test2.py
wujiantao.egg-info/PKG-INFO
wujiantao.egg-info/SOURCES.txt
wujiantao.egg-info/dependency_links.txt
wujiantao.egg-info/top_level.txt
wxz_decrpty/__init__.py