Metadata-Version: 2.1
Name: wujiantao
Version: 0.0.1
Summary: 微小助
Home-page: UNKNOWN
Author: wujiantao
Author-email: wujiantao1005@gmail.com
License: UNKNOWN
Platform: UNKNOWN
